genstack/__init__.py
genstack/genstack.py
genstack-0.2.0.dist-info/METADATA
genstack-0.2.0.dist-info/WHEEL
genstack-0.2.0.dist-info/RECORD
