Metadata-Version: 2.4
Name: genstack
Version: 0.2.0
Summary: Universal AI SDK from Genstack
Author-email: Shrey Kumar <shreyk.dev@gmail.com>
License: MIT
Requires-Dist: httpx
